__init__.py
drv_db_dao.py
drv_db_engine.py
drv_db_types.py
battery_cycler_drv_db-0.0.1.dist-info/LICENSE
battery_cycler_drv_db-0.0.1.dist-info/METADATA
battery_cycler_drv_db-0.0.1.dist-info/WHEEL
battery_cycler_drv_db-0.0.1.dist-info/top_level.txt
battery_cycler_drv_db-0.0.1.dist-info/RECORD
